__init__.py
layer.py
spatra-0.0.1.dist-info/METADATA
spatra-0.0.1.dist-info/WHEEL
spatra-0.0.1.dist-info/licenses/LICENSE
spatra-0.0.1.dist-info/RECORD
