Metadata-Version: 2.1
Name: spatra
Version: 0.0.1
Summary: spatra is a Python library to unify Spatial Transformers.
Project-URL: Homepage, https://github.com/pypa/sampleproject
Project-URL: Bug Tracker, https://github.com/pypa/sampleproject/issues
Author-email: Johann Schmidt <johann.schmidt@ovgu.de>
License-File: LICENSE
Classifier: License :: OSI Approved :: MIT License
Classifier: Operating System :: OS Independent
Classifier: Programming Language :: Python :: 3
Requires-Python: >=3.7
